howto_cli/__init__.py
howto_cli/cli.py
howto_cli/ai/__init__.py
howto_cli/ai/gateway.py
howto_cli/ai/providers.py
howto_cli/core/__init__.py
howto_cli/core/command_generator.py
howto_cli/core/config.py
howto_cli/models/__init__.py
howto_cli/models/command.py
howto_cli_ai-0.1.0.dist-info/licenses/LICENSE
howto_cli_ai-0.1.0.dist-info/METADATA
howto_cli_ai-0.1.0.dist-info/WHEEL
howto_cli_ai-0.1.0.dist-info/entry_points.txt
howto_cli_ai-0.1.0.dist-info/top_level.txt
howto_cli_ai-0.1.0.dist-info/RECORD
