Metadata-Version: 2.4
Name: howto-cli-ai
Version: 0.1.0
Summary: AI-powered CLI assistant for shell command generation
Author-email: How-to CLI <dev@howto-cli.com>
License-Expression: MIT
Keywords: cli,shell,ai,assistant,command-generation
Classifier: Development Status :: 3 - Alpha
Classifier: Intended Audience :: Developers
Classifier: Programming Language :: Python :: 3
Classifier: Programming Language :: Python :: 3.10
Classifier: Programming Language :: Python :: 3.11
Classifier: Programming Language :: Python :: 3.12
Requires-Python: >=3.10
License-File: LICENSE
Requires-Dist: typer>=0.9.0
Requires-Dist: pydantic>=2.0.0
Requires-Dist: rich>=13.0.0
Requires-Dist: google-generativeai>=0.3.0
Requires-Dist: openai>=1.0.0
Requires-Dist: groq>=0.4.0
Provides-Extra: dev
Requires-Dist: black>=23.0.0; extra == "dev"
Requires-Dist: ruff>=0.1.0; extra == "dev"
Requires-Dist: pytest>=7.0.0; extra == "dev"
Requires-Dist: pytest-cov>=4.0.0; extra == "dev"
Requires-Dist: mypy>=1.0.0; extra == "dev"
Requires-Dist: types-requests; extra == "dev"
Dynamic: license-file
